web_converter.py
web_converter-0.1.0.dist-info/LICENSE
web_converter-0.1.0.dist-info/METADATA
web_converter-0.1.0.dist-info/WHEEL
web_converter-0.1.0.dist-info/top_level.txt
web_converter-0.1.0.dist-info/RECORD
