Metadata-Version: 2.1
Name: web-converter
Version: 0.1.0
Summary: A package that converts headers and cookies
Author: ctyzan
License: This is free and unencumbered software released into the public domain.        
Project-URL: Homepage, https://github.com/ctyzan/web_converter
Project-URL: Bug Tracker, https://github.com/ctyzan/web_converter/issues
Classifier: Programming Language :: Python :: 3
Classifier: Operating System :: OS Independent
Requires-Python: >=3.6
License-File: LICENSE
